gamax/__init__.py
gamax/gamax.py
gamax-3.0.dist-info/METADATA
gamax-3.0.dist-info/WHEEL
gamax-3.0.dist-info/top_level.txt
gamax-3.0.dist-info/RECORD
