Metadata-Version: 2.4
Name: gamax
Version: 3.0
Summary: ...
Author: Alfisene Keita
Classifier: Programming Language :: Python :: 3
Classifier: License :: OSI Approved :: MIT License
Classifier: Operating System :: OS Independent
Requires-Dist: pycryptodome
Requires-Dist: cryptography
Dynamic: author
Dynamic: classifier
Dynamic: requires-dist
Dynamic: summary
